fastapi_custom_logger/__init__.py
fastapi_custom_logger/custom_logging.py
fastapi_custom_logger/logging_middleware.py
fastapi_custom_logger-0.1.0.dist-info/WHEEL
fastapi_custom_logger-0.1.0.dist-info/METADATA
fastapi_custom_logger-0.1.0.dist-info/RECORD
