Metadata-Version: 2.1
Name: fastapi-custom-logger
Version: 0.1.0
Summary: 
License: MIT
Author: Dominik Bucko
Author-email: domminik.bucko@pan-net.eu
Requires-Python: >=3.8,<4.0
Classifier: License :: OSI Approved :: MIT License
Classifier: Programming Language :: Python :: 3
Classifier: Programming Language :: Python :: 3.8
Classifier: Programming Language :: Python :: 3.9
Classifier: Programming Language :: Python :: 3.10
Classifier: Programming Language :: Python :: 3.11
Requires-Dist: fastapi (>=0.79.0,<0.80.0)
Requires-Dist: loguru (>=0.6.0,<0.7.0)
